larpixgeometry/__init__.py
larpixgeometry/pixelplane.py
larpixgeometry/layouts/__init__.py
larpixgeometry/layouts/draw_plane.py
larpixgeometry/layouts/layout-1.0.0.py
larpixgeometry/layouts/layout-1.1.0.py
larpixgeometry/layouts/layout-1.1.1.py
larpixgeometry/layouts/layout-1.1.2.py
larpixgeometry/layouts/layout-1.2.0.py
larpixgeometry/layouts/layout-1.2.1.py
larpixgeometry/layouts/layout-2.2.0.py
larpixgeometry/layouts/layout-2.2.1.py
larpixgeometry/layouts/layout-2.3.0.py
larpixgeometry/layouts/layout-2.4.0.py
larpixgeometry/layouts/layout-2.5.0.py
larpixgeometry/layouts/layout-2.5.1.py
larpixgeometry/layouts/layout-3.0.0.py
larpixgeometry/layouts/make-agnostic-hydra.py
larpixgeometry/layouts/multi_tile_layout.py
larpixgeometry/layouts/multi_tile_layout_NDLArModule.py
larpixgeometry/layouts/patterngenerator.py
larpixgeometry/layouts/variable_multi_tile_layout.py
larpix_geometry-0.4.0.dist-info/METADATA
larpix_geometry-0.4.0.dist-info/WHEEL
larpix_geometry-0.4.0.dist-info/top_level.txt
larpix_geometry-0.4.0.dist-info/RECORD
