Metadata-Version: 2.1
Name: larpix-geometry
Version: 0.4.0
Summary: LArPix sensor plane geometry
Home-page: https://github.com/samkohn/larpix-geometry
Author: Sam Kohn
Author-email: skohn@lbl.gov
Keywords: dune physics
Requires-Dist: pyyaml
Requires-Dist: reportlab
Requires-Dist: fire
